odoo/addons/ssi_batch_project_assignment_revenue_recognition/README.rst
odoo/addons/ssi_batch_project_assignment_revenue_recognition/__init__.py
odoo/addons/ssi_batch_project_assignment_revenue_recognition/__manifest__.py
odoo/addons/ssi_batch_project_assignment_revenue_recognition/i18n/ssi_batch_project_assignment_revenue_recognition.pot
odoo/addons/ssi_batch_project_assignment_revenue_recognition/i18n/ssi_project_assignment_revenue_recognition.pot
odoo/addons/ssi_batch_project_assignment_revenue_recognition/models/__init__.py
odoo/addons/ssi_batch_project_assignment_revenue_recognition/models/batch_project_assignment.py
odoo/addons/ssi_batch_project_assignment_revenue_recognition/static/description/icon.png
odoo/addons/ssi_batch_project_assignment_revenue_recognition/views/batch_project_assignment_views.xml
odoo14_addon_ssi_batch_project_assignment_revenue_recognition-14.0.1.0.1.dev1.dist-info/METADATA
odoo14_addon_ssi_batch_project_assignment_revenue_recognition-14.0.1.0.1.dev1.dist-info/WHEEL
odoo14_addon_ssi_batch_project_assignment_revenue_recognition-14.0.1.0.1.dev1.dist-info/top_level.txt
odoo14_addon_ssi_batch_project_assignment_revenue_recognition-14.0.1.0.1.dev1.dist-info/RECORD
